LICENSE
MANIFEST.in
README.md
setup.json
setup.py
rlgym/api/README.md
rlgym/api/__init__.py
rlgym/api/rlgym.py
rlgym/api/typing.py
rlgym/api/version.py
rlgym/api/config/__init__.py
rlgym/api/config/action_parser.py
rlgym/api/config/done_condition.py
rlgym/api/config/obs_builder.py
rlgym/api/config/renderer.py
rlgym/api/config/reward_function.py
rlgym/api/config/state_mutator.py
rlgym/api/config/transition_engine.py
rlgym_api.egg-info/PKG-INFO
rlgym_api.egg-info/SOURCES.txt
rlgym_api.egg-info/dependency_links.txt
rlgym_api.egg-info/top_level.txt