Metadata-Version: 2.1
Name: rlgym-api
Version: 2.0.0a1
Summary: A python API with zero dependencies to create fully customizable environments for Reinforcement Learning projects.
Home-page: https://rlgym.org
Author: Lucas Emery and Matthew Allen
Author-email: contact@rlgym.org
License: Apache 2.0
Project-URL: Source Code, https://github.com/lucas-emery/rocket-league-gym
Keywords: rocket-league,gym,reinforcement-learning,rlgym
Classifier: Development Status :: 4 - Beta
Classifier: License :: OSI Approved :: Apache Software License
Classifier: Programming Language :: Python :: 3
Classifier: Operating System :: OS Independent
Requires-Python: >=3.7
License-File: LICENSE
